arith_lib/__init__.py
arith_lib/arith.py
arith_lib-2.0.0.dist-info/LICENSE
arith_lib-2.0.0.dist-info/METADATA
arith_lib-2.0.0.dist-info/WHEEL
arith_lib-2.0.0.dist-info/top_level.txt
arith_lib-2.0.0.dist-info/RECORD
