Metadata-Version: 2.1
Name: arith-lib
Version: 2.0.0
Summary: A set of functions for miscellaneous arithmetic calculation
Home-page: UNKNOWN
Author: JM Allard
Author-email: jma214@gmail.com
License: UNKNOWN
Keywords: gcd lcm bezout pseudo prime miller rabin factorization divisor chinese remainder phi euler totient moebius base frobenius isqrt
Platform: UNKNOWN
Classifier: License :: OSI Approved :: MIT License
Classifier: Natural Language :: English
Classifier: Operating System :: OS Independent
Classifier: Programming Language :: Python :: 3.5
Classifier: Topic :: Scientific/Engineering :: Mathematics
